rufus/__init__.py
rufus/client.py
rufus/parse.py
rufus/scrape.py
rufus_web_scraper-1.0.3.dist-info/METADATA
rufus_web_scraper-1.0.3.dist-info/WHEEL
rufus_web_scraper-1.0.3.dist-info/entry_points.txt
rufus_web_scraper-1.0.3.dist-info/top_level.txt
rufus_web_scraper-1.0.3.dist-info/RECORD
